KorSEC/__init__.py
KorSEC/sec.py
KorSEC/sec_trainer.py
KorSEC/util.py
KorSEC/data/.DS_Store
KorSEC/data/sec.param
KorSEC/data/sec.dict/000005.ldb
KorSEC/data/sec.dict/000080.log
KorSEC/data/sec.dict/CURRENT
KorSEC/data/sec.dict/LOCK
KorSEC/data/sec.dict/LOG
KorSEC/data/sec.dict/LOG.old
KorSEC/data/sec.dict/MANIFEST-000079
KorSEC-1.0.2.dist-info/METADATA
KorSEC-1.0.2.dist-info/WHEEL
KorSEC-1.0.2.dist-info/top_level.txt
KorSEC-1.0.2.dist-info/RECORD
