Metadata-Version: 2.1
Name: KorSEC
Version: 1.0.2
Summary: Korean space error correction package
Home-page: https://github.com/seoyeon9646/KorSEC
Author: seoyeon9695
Author-email: seoyeon9695@gmail.com
License: MIT
Requires-Python: >=3
Requires-Dist: plyvel-wheels (==1.3.0)
Requires-Dist: tqdm (==4.64.1)
